orm2pydantic/__init__.py
orm2pydantic/sqla.py
orm2pydantic/utils.py
orm2pydantic-0.1.1.dist-info/COPYING
orm2pydantic-0.1.1.dist-info/COPYING.LESSER
orm2pydantic-0.1.1.dist-info/METADATA
orm2pydantic-0.1.1.dist-info/WHEEL
orm2pydantic-0.1.1.dist-info/top_level.txt
orm2pydantic-0.1.1.dist-info/RECORD
